emailnator/__init__.py
emailnator/emailnator.py
emailnator-0.1.1.dist-info/METADATA
emailnator-0.1.1.dist-info/WHEEL
emailnator-0.1.1.dist-info/top_level.txt
emailnator-0.1.1.dist-info/RECORD
