Metadata-Version: 2.1
Name: emailnator
Version: 0.1.1
Summary: A Python wrapper for the Emailnator temporary email service.
Home-page: https://github.com/repollo/emailnator
Author: repollo
Author-email: repollo.marrero@gmail.com
Keywords: emailnator wrapper temporary email
Requires-Dist: requests
Requires-Dist: python-dotenv
